nbdev_initial/__init__.py
nbdev_initial/_modidx.py
nbdev_initial/card.py
nbdev_initial/deck.py
nbdev_initial-0.0.1.dist-info/LICENSE
nbdev_initial-0.0.1.dist-info/METADATA
nbdev_initial-0.0.1.dist-info/WHEEL
nbdev_initial-0.0.1.dist-info/entry_points.txt
nbdev_initial-0.0.1.dist-info/top_level.txt
nbdev_initial-0.0.1.dist-info/RECORD
